{
  "$schema": "https://schema.management.azure.com/schemas/2019-04-01/deploymentParameters.json#",
  "contentVersion": "1.0.0.0",
  "parameters": {
    "renderClient": {
      "value": {
        "pythonUrl": "https://www.python.org/ftp/python/3.7.6/python-3.7.6-amd64.exe",
        "requirementsUrl": "https://raw.githubusercontent.com/AcademySoftwareFoundation/OpenCue/master/requirements_gui.txt",
        "pyCueUrl": "https://github.com/AcademySoftwareFoundation/OpenCue/releases/download/0.3.33/pycue-0.3.33-all.tar.gz",
        "pyOutlineUrl": "https://github.com/AcademySoftwareFoundation/OpenCue/releases/download/0.3.33/pyoutline-0.3.33-all.tar.gz",
        "cueSubmitUrl": "https://github.com/AcademySoftwareFoundation/OpenCue/releases/download/0.3.33/cuesubmit-0.3.33-all.tar.gz",
        "cueAdminUrl": "https://github.com/AcademySoftwareFoundation/OpenCue/releases/download/0.3.33/cueadmin-0.3.33-all.tar.gz",
        "cueGuiUrl": "https://github.com/AcademySoftwareFoundation/OpenCue/releases/download/0.3.33/cuegui-0.3.33-all.tar.gz"
      }
    },
    "imageBuilder": {
      "value": {
        "imageGalleryName": "",
        "imageTemplateName": "RenderClient",
        "imageSourceType": "PlatformImage",
        "imageBuildTimeoutMinutes": 30,
        "imageReplicationCount": 1,
        "imageReplicationRegions": [
        ]
      }
    }
  }
}
