{
  "jobId": {
    "value": "job4"
  },
  "poolId": {
    "value": "pool1"
  },
  "adminUsername": {
    "value": "azureuser"
  },
  "frameStart": {
    "value": 0
  },
  "frameEnd": {
    "value": 499
  },
  "frameStep": {
    "value": 1
  },
  "mayaProjectPath": {
    "value": "/nfs/default/demoscene/candle_MA"
  },
  "sceneFile": {
    "value": "/nfs/default/demoscene/candle_MA/candles_MA.ma"
  },  
  "imagesOutputBasePath": {
    "value": "/nfs/default/images"
  },
  "renderScriptPath": {
    "value": "/nfs/default/src/render.sh"
  },
  "debugPath": {
    "value": "/nfs/default/debug"
  },
  "additionalFlags": {
    "value": " -fnc name.#.ext "
  }
}