{
  "$schema": "https://schema.management.azure.com/schemas/2015-01-01/deploymentTemplate.json#",
  "contentVersion": "1.0.0.0",
  "parameters": {
    "controllerName": {
      "type": "string",
      "metadata": {
        "description": "The unique name used for resource names associated with the controller"
      }
    },
    "controllerAdminUsername": {
      "type": "string",
      "defaultValue": "azureuser",
      "metadata": {
        "description": "The controller admin username."
      }
    },
    "controllerAdminPassword": {
      "type": "securestring",
      "metadata": {
        "description": "The controller admin password."
      }
    }
  },
  "variables": {
    "controllerName": "[parameters('controllerName')]",
    "controllerAdminUsername": "[parameters('controllerAdminUsername')]",
    "controllerAdminPassword": "[parameters('controllerAdminPassword')]",
    "nicName": "[concat('vmnic-',variables('controllerName'))]",
    "addressPrefix": "172.16.0.0/16",
    "subnetName": "[concat('subnet-',variables('controllerName'))]",
    "subnetPrefix": "172.16.0.0/24",
    "publicIPAddressName": "[concat('publicip-',variables('controllerName'))]",
    "vmName": "[concat('vm-',variables('controllerName'))]",
    "virtualNetworkName": "[concat('vnet-',variables('controllerName'))]",
    "vnetID": "[resourceId('Microsoft.Network/virtualNetworks',variables('virtualNetworkName'))]",
    "subnetRef": "[concat(variables('vnetID'),'/subnets/',variables('subnetName'))]",
    "vmSize": "Standard_A1_v2"
  },
  "resources": [
    {
      "apiVersion": "2017-10-01",
      "type": "Microsoft.Network/publicIPAddresses",
      "name": "[variables('publicIPAddressName')]",
      "location": "[resourceGroup().location]",
      "properties": {
        "publicIPAllocationMethod": "Static"
      }
    },
    {
      "apiVersion": "2017-10-01",
      "type": "Microsoft.Network/virtualNetworks",
      "name": "[variables('virtualNetworkName')]",
      "location": "[resourceGroup().location]",
      "properties": {
        "addressSpace": {
          "addressPrefixes": [
            "[variables('addressPrefix')]"
          ]
        },
        "subnets": [
          {
            "name": "[variables('subnetName')]",
            "properties": {
              "addressPrefix": "[variables('subnetPrefix')]"
            }
          }
        ]
      }
    },
    {
      "apiVersion": "2017-10-01",
      "type": "Microsoft.Network/networkInterfaces",
      "name": "[variables('nicName')]",
      "location": "[resourceGroup().location]",
      "dependsOn": [
        "[concat('Microsoft.Network/publicIPAddresses/', variables('publicIPAddressName'))]",
        "[concat('Microsoft.Network/virtualNetworks/', variables('virtualNetworkName'))]"
      ],
      "properties": {
        "ipConfigurations": [
          {
            "name": "ipconfig",
            "properties": {
              "privateIPAllocationMethod": "Dynamic",
              "publicIPAddress": {
                "id": "[resourceId('Microsoft.Network/publicIPAddresses',variables('publicIPAddressName'))]"
              },
              "subnet": {
                "id": "[variables('subnetRef')]"
              }
            }
          }
        ]
      }
    },
    {
      "apiVersion": "2017-12-01",
      "type": "Microsoft.Compute/virtualMachines",
      "name": "[variables('vmName')]",
      "location": "[resourceGroup().location]",
      "plan": {
        "name": "avere-vfx-controller",
        "publisher": "microsoft-avere",
        "product": "vfxt"
      },
      "dependsOn": [
        "[concat('Microsoft.Network/networkInterfaces/', variables('nicName'))]"
      ],
      "properties": {
        "hardwareProfile": {
          "vmSize": "[variables('vmSize')]"
        },
        "osProfile": {
          "computername": "[variables('vmName')]",
          "controllerAdminUsername": "[variables('controllerAdminUsername')]",
          "controllerAdminPassword": "[variables('controllerAdminPassword')]"
        },
        "storageProfile": {
          "imageReference": {
            "publisher": "microsoft-avere",
            "offer": "vfxt",
            "sku": "avere-vfx-controller",
            "version": "latest"
          }
        },
        "networkProfile": {
          "networkInterfaces": [
            {
              "id": "[resourceId('Microsoft.Network/networkInterfaces',variables('nicName'))]"
            }
          ]
        }
      }
    }
  ],
  "outputs": {
    "RESOURCE_GROUP": {
      "type": "string",
      "value": "[resourceGroup().name]"
    },
    "LOCATION": {
      "type": "string",
      "value": "[resourceGroup().location]"
    },
    "NETWORK": {
      "type": "string",
      "value": "[variables('virtualNetworkName')]"
    },
    "SUBNET": {
      "type": "string",
      "value": "[variables('subnetName')]"
    },
    "SUBNET_ID": {
      "type": "string",
      "value": "[concat(resourceId('Microsoft.Network/virtualNetworks',variables('virtualNetworkName')),'/subnets/',variables('subnetName'))]"
    },
    "sshString": {
      "type": "string",
      "value": "[concat('ssh ', variables('controllerAdminUsername'), '@', reference(resourceId('Microsoft.Network/publicIPAddresses/', variables('publicIPAddressName'))).ipAddress)]"
    }
  }
}
